spft/__init__.py
spft/multiprocess.py
spft-0.0.4.dist-info/LICENSE
spft-0.0.4.dist-info/METADATA
spft-0.0.4.dist-info/WHEEL
spft-0.0.4.dist-info/top_level.txt
spft-0.0.4.dist-info/RECORD
